pydefect/__init__.py
pydefect/defaults.py
pydefect/error.py
pydefect/analyzer/__init__.py
pydefect/analyzer/_defect_charge_distribution.py
pydefect/analyzer/band_edge_states.py
pydefect/analyzer/calc_results.py
pydefect/analyzer/calc_summary.py
pydefect/analyzer/defect_charge_info.py
pydefect/analyzer/defect_energy.py
pydefect/analyzer/defect_energy_plotter.py
pydefect/analyzer/defect_energy_util.py
pydefect/analyzer/defect_structure_comparator.py
pydefect/analyzer/defect_structure_info.py
pydefect/analyzer/eigenvalue_plotter.py
pydefect/analyzer/grids.py
pydefect/analyzer/make_band_edge_states.py
pydefect/analyzer/make_calc_summary.py
pydefect/analyzer/make_defect_energy_info.py
pydefect/analyzer/make_defect_energy_summary.py
pydefect/analyzer/make_defect_structure_info.py
pydefect/analyzer/pinning_levels.py
pydefect/analyzer/refine_defect_structure.py
pydefect/analyzer/transition_levels.py
pydefect/analyzer/transition_levels_plotter.py
pydefect/analyzer/unitcell.py
pydefect/analyzer/concentration/__init__.py
pydefect/analyzer/concentration/concentration.py
pydefect/analyzer/concentration/degeneracy.py
pydefect/analyzer/concentration/distribution_function.py
pydefect/analyzer/concentration/make_concentration.py
pydefect/analyzer/concentration/plot_concentration.py
pydefect/chem_pot_diag/__init__.py
pydefect/chem_pot_diag/chem_pot_diag.py
pydefect/chem_pot_diag/cpd_plotter.py
pydefect/cli/__init__.py
pydefect/cli/main.py
pydefect/cli/main_functions.py
pydefect/cli/main_print_json.py
pydefect/cli/main_tools.py
pydefect/cli/main_util.py
pydefect/cli/main_util_functions.py
pydefect/cli/make_defect_vesta_file.py
pydefect/cli/vasp/__init__.py
pydefect/cli/vasp/get_defect_charge_state.py
pydefect/cli/vasp/main_vasp.py
pydefect/cli/vasp/main_vasp_functions.py
pydefect/cli/vasp/main_vasp_util.py
pydefect/cli/vasp/main_vasp_util_functions.py
pydefect/cli/vasp/make_band_edge_orbital_infos.py
pydefect/cli/vasp/make_calc_results.py
pydefect-0.9.8.dist-info/LICENSE
pydefect-0.9.8.dist-info/METADATA
pydefect-0.9.8.dist-info/WHEEL
pydefect-0.9.8.dist-info/entry_points.txt
pydefect-0.9.8.dist-info/top_level.txt
pydefect-0.9.8.dist-info/RECORD
