Metadata-Version: 2.1
Name: pydefect
Version: 0.9.8
Summary: Integrated environment for first-principles point-defect calculations
Home-page: https://github.com/kumagai-group/pydefect
Author: Yu Kumagai
Author-email: yuuukuma@gmail.com
License: MIT license
Platform: UNKNOWN
Classifier: Programming Language :: Python :: 3.7
Classifier: License :: OSI Approved :: MIT License
Requires-Dist: numpy
Requires-Dist: monty
Requires-Dist: pymatgen
Requires-Dist: vise
Requires-Dist: tabulate
Requires-Dist: adjustText
Requires-Dist: matplotlib-label-lines
